notifier/__init__.py
notifier/discord_notifier.py
dugudugu_discord_notifier-0.3.0.dist-info/METADATA
dugudugu_discord_notifier-0.3.0.dist-info/WHEEL
dugudugu_discord_notifier-0.3.0.dist-info/RECORD
