Metadata-Version: 2.1
Name: dugudugu-discord-notifier
Version: 0.3.0
Summary: A simple Discord notification tool using webhooks
Home-page: https://github.com/taejun0622/notifier
License: MIT
Keywords: discord,webhook,notification,bot
Author: taejun
Author-email: dugudugu0622@gmail.com
Requires-Python: >=3.7,<4.0
Classifier: Development Status :: 4 - Beta
Classifier: Intended Audience :: Developers
Classifier: License :: OSI Approved :: MIT License
Classifier: Programming Language :: Python :: 3
Classifier: Programming Language :: Python :: 3.7
Classifier: Programming Language :: Python :: 3.8
Classifier: Programming Language :: Python :: 3.9
Classifier: Programming Language :: Python :: 3.10
Classifier: Programming Language :: Python :: 3.11
Classifier: Programming Language :: Python :: 3.12
Classifier: Programming Language :: Python :: 3.13
Classifier: Topic :: Communications
Classifier: Topic :: Software Development :: Libraries :: Python Modules
Requires-Dist: requests (>=2.31.0,<3.0.0)
Project-URL: Repository, https://github.com/taejun0622/notifier
